{
  "bankName": "Bank A",
  "accountType": "checking",
  "balance": 18640,
  "transactions": [
    { "id": "txn_a_001", "date": "2026-05-16", "description": "Getir Market Büyük Sipariş", "amount": 412, "type": "expense", "category": "Market", "source": "Bank A" },
    { "id": "txn_a_002", "date": "2026-05-16", "description": "İETT İstanbulkart Yükleme", "amount": 300, "type": "expense", "category": "Ulaşım", "source": "Bank A" },
    { "id": "txn_a_003", "date": "2026-05-15", "description": "Yemeksepeti", "amount": 267, "type": "expense", "category": "Yemek", "source": "Bank A" },
    { "id": "txn_a_004", "date": "2026-05-15", "description": "Starbucks Caddebostan", "amount": 268, "type": "expense", "category": "Kahve", "source": "Bank A" },
    { "id": "txn_a_005", "date": "2026-05-14", "description": "Migros Sanal Market", "amount": 738, "type": "expense", "category": "Market", "source": "Bank A" },
    { "id": "txn_a_006", "date": "2026-05-14", "description": "BiTaksi", "amount": 152, "type": "expense", "category": "Ulaşım", "source": "Bank A" },
    { "id": "txn_a_007", "date": "2026-05-13", "description": "Trendyol Yemek", "amount": 189, "type": "expense", "category": "Yemek", "source": "Bank A" },
    { "id": "txn_a_008", "date": "2026-05-13", "description": "A101 Market", "amount": 243, "type": "expense", "category": "Market", "source": "Bank A" },
    { "id": "txn_a_009", "date": "2026-05-12", "description": "Starbucks Bağdat Caddesi", "amount": 254, "type": "expense", "category": "Kahve", "source": "Bank A" },
    { "id": "txn_a_010", "date": "2026-05-12", "description": "Akaryakıt - Opet Kadıköy", "amount": 870, "type": "expense", "category": "Ulaşım", "source": "Bank A" },
    { "id": "txn_a_011", "date": "2026-05-11", "description": "Carrefour Express", "amount": 384, "type": "expense", "category": "Market", "source": "Bank A" },
    { "id": "txn_a_012", "date": "2026-05-10", "description": "Yemeksepeti", "amount": 143, "type": "expense", "category": "Yemek", "source": "Bank A" },
    { "id": "txn_a_013", "date": "2026-05-10", "description": "Elektrik Faturası - BEDAŞ", "amount": 680, "type": "expense", "category": "Faturalar", "source": "Bank A" },
    { "id": "txn_a_014", "date": "2026-05-09", "description": "Kahve Dünyası Moda", "amount": 147, "type": "expense", "category": "Kahve", "source": "Bank A" },
    { "id": "txn_a_015", "date": "2026-05-09", "description": "BİM Market", "amount": 276, "type": "expense", "category": "Market", "source": "Bank A" },
    { "id": "txn_a_016", "date": "2026-05-08", "description": "Doğalgaz Faturası - İGDAŞ", "amount": 430, "type": "expense", "category": "Faturalar", "source": "Bank A" },
    { "id": "txn_a_017", "date": "2026-05-08", "description": "Martı Scooter", "amount": 248, "type": "expense", "category": "Ulaşım", "source": "Bank A" },
    { "id": "txn_a_018", "date": "2026-05-07", "description": "Getir Market Büyük Sipariş", "amount": 397, "type": "expense", "category": "Market", "source": "Bank A" },
    { "id": "txn_a_019", "date": "2026-05-06", "description": "Su Faturası - İSKİ", "amount": 178, "type": "expense", "category": "Faturalar", "source": "Bank A" },
    { "id": "txn_a_020", "date": "2026-05-05", "description": "Tim Hortons Kadıköy", "amount": 135, "type": "expense", "category": "Kahve", "source": "Bank A" },
    { "id": "txn_a_021", "date": "2026-05-04", "description": "Migros Sanal Market", "amount": 824, "type": "expense", "category": "Market", "source": "Bank A" },
    { "id": "txn_a_022", "date": "2026-05-03", "description": "Trendyol Yemek", "amount": 218, "type": "expense", "category": "Yemek", "source": "Bank A" },
    { "id": "txn_a_023", "date": "2026-05-02", "description": "İETT İstanbulkart Yükleme", "amount": 200, "type": "expense", "category": "Ulaşım", "source": "Bank A" },
    { "id": "txn_a_024", "date": "2026-05-01", "description": "Maaş Ödemesi - Mayıs", "amount": 70000, "type": "income", "category": "Maaş", "source": "Bank A" },
    { "id": "txn_a_025", "date": "2026-04-30", "description": "Yemeksepeti", "amount": 312, "type": "expense", "category": "Yemek", "source": "Bank A" },
    { "id": "txn_a_026", "date": "2026-04-29", "description": "Starbucks Nişantaşı", "amount": 274, "type": "expense", "category": "Kahve", "source": "Bank A" },
    { "id": "txn_a_027", "date": "2026-04-28", "description": "A101 Market", "amount": 318, "type": "expense", "category": "Market", "source": "Bank A" },
    { "id": "txn_a_028", "date": "2026-04-27", "description": "Getir Market", "amount": 204, "type": "expense", "category": "Market", "source": "Bank A" },
    { "id": "txn_a_029", "date": "2026-04-26", "description": "BiTaksi", "amount": 388, "type": "expense", "category": "Ulaşım", "source": "Bank A" },
    { "id": "txn_a_030", "date": "2026-04-25", "description": "Migros Sanal Market", "amount": 653, "type": "expense", "category": "Market", "source": "Bank A" },
    { "id": "txn_a_031", "date": "2026-04-24", "description": "Trendyol Yemek Öğle", "amount": 176, "type": "expense", "category": "Yemek", "source": "Bank A" },
    { "id": "txn_a_032", "date": "2026-04-23", "description": "Starbucks Etiler", "amount": 251, "type": "expense", "category": "Kahve", "source": "Bank A" },
    { "id": "txn_a_033", "date": "2026-04-22", "description": "Akaryakıt - Shell Ataşehir", "amount": 920, "type": "expense", "category": "Ulaşım", "source": "Bank A" },
    { "id": "txn_a_034", "date": "2026-04-21", "description": "BİM Market", "amount": 289, "type": "expense", "category": "Market", "source": "Bank A" },
    { "id": "txn_a_035", "date": "2026-04-20", "description": "Yemeksepeti", "amount": 241, "type": "expense", "category": "Yemek", "source": "Bank A" },
    { "id": "txn_a_036", "date": "2026-04-18", "description": "Elektrik Faturası - BEDAŞ", "amount": 614, "type": "expense", "category": "Faturalar", "source": "Bank A" },
    { "id": "txn_a_037", "date": "2026-04-16", "description": "Carrefour Express", "amount": 341, "type": "expense", "category": "Market", "source": "Bank A" },
    { "id": "txn_a_038", "date": "2026-04-14", "description": "Doğalgaz Faturası - İGDAŞ", "amount": 392, "type": "expense", "category": "Faturalar", "source": "Bank A" },
    { "id": "txn_a_039", "date": "2026-04-13", "description": "Kahve Dünyası Bağdat", "amount": 139, "type": "expense", "category": "Kahve", "source": "Bank A" },
    { "id": "txn_a_040", "date": "2026-04-11", "description": "Uber", "amount": 124, "type": "expense", "category": "Ulaşım", "source": "Bank A" },
    { "id": "txn_a_041", "date": "2026-04-08", "description": "Su Faturası - İSKİ", "amount": 163, "type": "expense", "category": "Faturalar", "source": "Bank A" },
    { "id": "txn_a_042", "date": "2026-04-06", "description": "Getir Market Büyük Sipariş", "amount": 528, "type": "expense", "category": "Market", "source": "Bank A" },
    { "id": "txn_a_043", "date": "2026-04-04", "description": "Trendyol Yemek", "amount": 198, "type": "expense", "category": "Yemek", "source": "Bank A" },
    { "id": "txn_a_044", "date": "2026-04-01", "description": "Maaş Ödemesi - Nisan", "amount": 70000, "type": "income", "category": "Maaş", "source": "Bank A" },
    { "id": "txn_a_045", "date": "2026-03-31", "description": "Migros Sanal Market", "amount": 754, "type": "expense", "category": "Market", "source": "Bank A" },
    { "id": "txn_a_046", "date": "2026-03-29", "description": "Yemeksepeti", "amount": 289, "type": "expense", "category": "Yemek", "source": "Bank A" },
    { "id": "txn_a_047", "date": "2026-03-28", "description": "Starbucks Levent", "amount": 262, "type": "expense", "category": "Kahve", "source": "Bank A" },
    { "id": "txn_a_048", "date": "2026-03-27", "description": "BiTaksi", "amount": 203, "type": "expense", "category": "Ulaşım", "source": "Bank A" },
    { "id": "txn_a_049", "date": "2026-03-26", "description": "A101 Market", "amount": 296, "type": "expense", "category": "Market", "source": "Bank A" },
    { "id": "txn_a_050", "date": "2026-03-25", "description": "Getir Market", "amount": 381, "type": "expense", "category": "Market", "source": "Bank A" },
    { "id": "txn_a_051", "date": "2026-03-24", "description": "Akaryakıt - Opet Üsküdar", "amount": 870, "type": "expense", "category": "Ulaşım", "source": "Bank A" },
    { "id": "txn_a_052", "date": "2026-03-20", "description": "Elektrik Faturası - BEDAŞ", "amount": 598, "type": "expense", "category": "Faturalar", "source": "Bank A" },
    { "id": "txn_a_053", "date": "2026-03-18", "description": "Trendyol Yemek", "amount": 213, "type": "expense", "category": "Yemek", "source": "Bank A" },
    { "id": "txn_a_054", "date": "2026-03-15", "description": "Doğalgaz Faturası - İGDAŞ", "amount": 564, "type": "expense", "category": "Faturalar", "source": "Bank A" },
    { "id": "txn_a_055", "date": "2026-03-14", "description": "Kahve Dünyası Moda", "amount": 126, "type": "expense", "category": "Kahve", "source": "Bank A" },
    { "id": "txn_a_056", "date": "2026-03-12", "description": "Migros Sanal Market", "amount": 812, "type": "expense", "category": "Market", "source": "Bank A" },
    { "id": "txn_a_057", "date": "2026-03-10", "description": "İETT İstanbulkart Yükleme", "amount": 300, "type": "expense", "category": "Ulaşım", "source": "Bank A" },
    { "id": "txn_a_058", "date": "2026-03-08", "description": "Su Faturası - İSKİ", "amount": 172, "type": "expense", "category": "Faturalar", "source": "Bank A" },
    { "id": "txn_a_059", "date": "2026-03-06", "description": "Yemeksepeti", "amount": 334, "type": "expense", "category": "Yemek", "source": "Bank A" },
    { "id": "txn_a_060", "date": "2026-03-04", "description": "Starbucks Beşiktaş", "amount": 477, "type": "expense", "category": "Kahve", "source": "Bank A" },
    { "id": "txn_a_061", "date": "2026-03-03", "description": "BİM Market", "amount": 421, "type": "expense", "category": "Market", "source": "Bank A" },
    { "id": "txn_a_062", "date": "2026-03-01", "description": "Maaş Ödemesi - Mart", "amount": 70000, "type": "income", "category": "Maaş", "source": "Bank A" },
    { "id": "txn_a_063", "date": "2026-02-28", "description": "Getir Market Büyük Sipariş", "amount": 354, "type": "expense", "category": "Market", "source": "Bank A" },
    { "id": "txn_a_064", "date": "2026-02-27", "description": "BiTaksi", "amount": 194, "type": "expense", "category": "Ulaşım", "source": "Bank A" },
    { "id": "txn_a_065", "date": "2026-02-25", "description": "Trendyol Yemek", "amount": 187, "type": "expense", "category": "Yemek", "source": "Bank A" },
    { "id": "txn_a_066", "date": "2026-02-24", "description": "Migros Sanal Market", "amount": 643, "type": "expense", "category": "Market", "source": "Bank A" },
    { "id": "txn_a_067", "date": "2026-02-22", "description": "Starbucks Nişantaşı", "amount": 369, "type": "expense", "category": "Kahve", "source": "Bank A" },
    { "id": "txn_a_068", "date": "2026-02-20", "description": "Elektrik Faturası - BEDAŞ", "amount": 745, "type": "expense", "category": "Faturalar", "source": "Bank A" },
    { "id": "txn_a_069", "date": "2026-02-19", "description": "Akaryakıt - Shell Bakırköy", "amount": 910, "type": "expense", "category": "Ulaşım", "source": "Bank A" },
    { "id": "txn_a_070", "date": "2026-02-17", "description": "A101 Market", "amount": 307, "type": "expense", "category": "Market", "source": "Bank A" },
    { "id": "txn_a_071", "date": "2026-02-14", "description": "Yemeksepeti", "amount": 278, "type": "expense", "category": "Yemek", "source": "Bank A" },
    { "id": "txn_a_072", "date": "2026-02-12", "description": "Doğalgaz Faturası - İGDAŞ", "amount": 720, "type": "expense", "category": "Faturalar", "source": "Bank A" },
    { "id": "txn_a_073", "date": "2026-02-10", "description": "Su Faturası - İSKİ", "amount": 158, "type": "expense", "category": "Faturalar", "source": "Bank A" },
    { "id": "txn_a_074", "date": "2026-02-08", "description": "Kahve Dünyası Bağdat", "amount": 144, "type": "expense", "category": "Kahve", "source": "Bank A" },
    { "id": "txn_a_075", "date": "2026-02-06", "description": "Getir Market", "amount": 398, "type": "expense", "category": "Market", "source": "Bank A" },
    { "id": "txn_a_076", "date": "2026-02-04", "description": "İETT İstanbulkart Yükleme", "amount": 200, "type": "expense", "category": "Ulaşım", "source": "Bank A" },
    { "id": "txn_a_077", "date": "2026-02-01", "description": "Maaş Ödemesi - Şubat", "amount": 70000, "type": "income", "category": "Maaş", "source": "Bank A" },
    { "id": "txn_a_078", "date": "2026-01-30", "description": "Migros Sanal Market", "amount": 718, "type": "expense", "category": "Market", "source": "Bank A" },
    { "id": "txn_a_079", "date": "2026-01-28", "description": "Yemeksepeti", "amount": 256, "type": "expense", "category": "Yemek", "source": "Bank A" },
    { "id": "txn_a_080", "date": "2026-01-26", "description": "Starbucks Kadıköy", "amount": 261, "type": "expense", "category": "Kahve", "source": "Bank A" },
    { "id": "txn_a_081", "date": "2026-01-24", "description": "Akaryakıt - Opet Maltepe", "amount": 880, "type": "expense", "category": "Ulaşım", "source": "Bank A" },
    { "id": "txn_a_082", "date": "2026-01-22", "description": "Elektrik Faturası - BEDAŞ", "amount": 810, "type": "expense", "category": "Faturalar", "source": "Bank A" },
    { "id": "txn_a_083", "date": "2026-01-20", "description": "A101 Market", "amount": 284, "type": "expense", "category": "Market", "source": "Bank A" },
    { "id": "txn_a_084", "date": "2026-01-18", "description": "Carrefour Express", "amount": 392, "type": "expense", "category": "Market", "source": "Bank A" },
    { "id": "txn_a_085", "date": "2026-01-16", "description": "Doğalgaz Faturası - İGDAŞ", "amount": 840, "type": "expense", "category": "Faturalar", "source": "Bank A" },
    { "id": "txn_a_086", "date": "2026-01-14", "description": "Trendyol Yemek", "amount": 202, "type": "expense", "category": "Yemek", "source": "Bank A" },
    { "id": "txn_a_087", "date": "2026-01-12", "description": "Getir Market Büyük Sipariş", "amount": 443, "type": "expense", "category": "Market", "source": "Bank A" },
    { "id": "txn_a_088", "date": "2026-01-10", "description": "Su Faturası - İSKİ", "amount": 167, "type": "expense", "category": "Faturalar", "source": "Bank A" },
    { "id": "txn_a_089", "date": "2026-01-09", "description": "BiTaksi", "amount": 216, "type": "expense", "category": "Ulaşım", "source": "Bank A" },
    { "id": "txn_a_090", "date": "2026-01-07", "description": "Tim Hortons Üsküdar", "amount": 138, "type": "expense", "category": "Kahve", "source": "Bank A" },
    { "id": "txn_a_091", "date": "2026-01-05", "description": "Migros Sanal Market", "amount": 697, "type": "expense", "category": "Market", "source": "Bank A" },
    { "id": "txn_a_092", "date": "2026-01-03", "description": "Yemeksepeti", "amount": 291, "type": "expense", "category": "Yemek", "source": "Bank A" },
    { "id": "txn_a_093", "date": "2026-01-01", "description": "Maaş Ödemesi - Ocak", "amount": 70000, "type": "income", "category": "Maaş", "source": "Bank A" },
    { "id": "txn_a_094", "date": "2025-12-31", "description": "Getir Market Büyük Sipariş", "amount": 512, "type": "expense", "category": "Market", "source": "Bank A" },
    { "id": "txn_a_095", "date": "2025-12-30", "description": "Akaryakıt - Shell Ümraniye", "amount": 950, "type": "expense", "category": "Ulaşım", "source": "Bank A" },
    { "id": "txn_a_096", "date": "2025-12-28", "description": "Yemeksepeti", "amount": 334, "type": "expense", "category": "Yemek", "source": "Bank A" },
    { "id": "txn_a_097", "date": "2025-12-27", "description": "Starbucks Etiler", "amount": 283, "type": "expense", "category": "Kahve", "source": "Bank A" },
    { "id": "txn_a_098", "date": "2025-12-26", "description": "Migros Sanal Market", "amount": 1240, "type": "expense", "category": "Market", "source": "Bank A" },
    { "id": "txn_a_099", "date": "2025-12-24", "description": "Elektrik Faturası - BEDAŞ", "amount": 790, "type": "expense", "category": "Faturalar", "source": "Bank A" },
    { "id": "txn_a_100", "date": "2025-12-22", "description": "A101 Market", "amount": 356, "type": "expense", "category": "Market", "source": "Bank A" },
    { "id": "txn_a_101", "date": "2025-12-20", "description": "Doğalgaz Faturası - İGDAŞ", "amount": 920, "type": "expense", "category": "Faturalar", "source": "Bank A" },
    { "id": "txn_a_102", "date": "2025-12-18", "description": "Trendyol Yemek", "amount": 227, "type": "expense", "category": "Yemek", "source": "Bank A" },
    { "id": "txn_a_103", "date": "2025-12-16", "description": "İETT İstanbulkart Yükleme", "amount": 300, "type": "expense", "category": "Ulaşım", "source": "Bank A" },
    { "id": "txn_a_104", "date": "2025-12-14", "description": "Kahve Dünyası Caddebostan", "amount": 142, "type": "expense", "category": "Kahve", "source": "Bank A" },
    { "id": "txn_a_105", "date": "2025-12-12", "description": "Su Faturası - İSKİ", "amount": 163, "type": "expense", "category": "Faturalar", "source": "Bank A" },
    { "id": "txn_a_106", "date": "2025-12-10", "description": "Carrefour Express", "amount": 478, "type": "expense", "category": "Market", "source": "Bank A" },
    { "id": "txn_a_107", "date": "2025-12-05", "description": "Yıl Sonu İkramiyesi", "amount": 20000, "type": "income", "category": "Maaş", "source": "Bank A" },
    { "id": "txn_a_108", "date": "2025-12-04", "description": "BiTaksi", "amount": 289, "type": "expense", "category": "Ulaşım", "source": "Bank A" },
    { "id": "txn_a_109", "date": "2025-12-01", "description": "Maaş Ödemesi - Aralık", "amount": 70000, "type": "income", "category": "Maaş", "source": "Bank A" },
    { "id": "txn_a_110", "date": "2025-11-29", "description": "Migros Sanal Market", "amount": 862, "type": "expense", "category": "Market", "source": "Bank A" },
    { "id": "txn_a_111", "date": "2025-11-27", "description": "Akaryakıt - Opet Kadıköy", "amount": 880, "type": "expense", "category": "Ulaşım", "source": "Bank A" },
    { "id": "txn_a_112", "date": "2025-11-25", "description": "Yemeksepeti", "amount": 267, "type": "expense", "category": "Yemek", "source": "Bank A" },
    { "id": "txn_a_113", "date": "2025-11-23", "description": "Getir Market Büyük Sipariş", "amount": 488, "type": "expense", "category": "Market", "source": "Bank A" },
    { "id": "txn_a_114", "date": "2025-11-20", "description": "Elektrik Faturası - BEDAŞ", "amount": 640, "type": "expense", "category": "Faturalar", "source": "Bank A" },
    { "id": "txn_a_115", "date": "2025-11-18", "description": "Starbucks Levent", "amount": 255, "type": "expense", "category": "Kahve", "source": "Bank A" },
    { "id": "txn_a_116", "date": "2025-11-16", "description": "A101 Market", "amount": 312, "type": "expense", "category": "Market", "source": "Bank A" },
    { "id": "txn_a_117", "date": "2025-11-14", "description": "Doğalgaz Faturası - İGDAŞ", "amount": 480, "type": "expense", "category": "Faturalar", "source": "Bank A" },
    { "id": "txn_a_118", "date": "2025-11-12", "description": "Trendyol Yemek", "amount": 194, "type": "expense", "category": "Yemek", "source": "Bank A" },
    { "id": "txn_a_119", "date": "2025-11-10", "description": "İETT İstanbulkart Yükleme", "amount": 200, "type": "expense", "category": "Ulaşım", "source": "Bank A" },
    { "id": "txn_a_120", "date": "2025-11-08", "description": "Su Faturası - İSKİ", "amount": 176, "type": "expense", "category": "Faturalar", "source": "Bank A" },
    { "id": "txn_a_121", "date": "2025-11-06", "description": "BİM Market", "amount": 349, "type": "expense", "category": "Market", "source": "Bank A" },
    { "id": "txn_a_122", "date": "2025-11-04", "description": "Kahve Dünyası Moda", "amount": 131, "type": "expense", "category": "Kahve", "source": "Bank A" },
    { "id": "txn_a_123", "date": "2025-11-01", "description": "Maaş Ödemesi - Kasım", "amount": 70000, "type": "income", "category": "Maaş", "source": "Bank A" },
    { "id": "txn_a_124", "date": "2025-10-30", "description": "Migros Sanal Market", "amount": 731, "type": "expense", "category": "Market", "source": "Bank A" },
    { "id": "txn_a_125", "date": "2025-10-28", "description": "Getir Market", "amount": 403, "type": "expense", "category": "Market", "source": "Bank A" },
    { "id": "txn_a_126", "date": "2025-10-26", "description": "Yemeksepeti", "amount": 243, "type": "expense", "category": "Yemek", "source": "Bank A" },
    { "id": "txn_a_127", "date": "2025-10-24", "description": "Akaryakıt - Shell Maltepe", "amount": 860, "type": "expense", "category": "Ulaşım", "source": "Bank A" },
    { "id": "txn_a_128", "date": "2025-10-22", "description": "Starbucks Bağdat Caddesi", "amount": 170, "type": "expense", "category": "Kahve", "source": "Bank A" },
    { "id": "txn_a_129", "date": "2025-10-20", "description": "Elektrik Faturası - BEDAŞ", "amount": 524, "type": "expense", "category": "Faturalar", "source": "Bank A" },
    { "id": "txn_a_130", "date": "2025-10-18", "description": "A101 Market", "amount": 268, "type": "expense", "category": "Market", "source": "Bank A" },
    { "id": "txn_a_131", "date": "2025-10-16", "description": "Doğalgaz Faturası - İGDAŞ", "amount": 320, "type": "expense", "category": "Faturalar", "source": "Bank A" },
    { "id": "txn_a_132", "date": "2025-10-14", "description": "Trendyol Yemek", "amount": 176, "type": "expense", "category": "Yemek", "source": "Bank A" },
    { "id": "txn_a_133", "date": "2025-10-12", "description": "İETT İstanbulkart Yükleme", "amount": 300, "type": "expense", "category": "Ulaşım", "source": "Bank A" },
    { "id": "txn_a_134", "date": "2025-10-10", "description": "Su Faturası - İSKİ", "amount": 154, "type": "expense", "category": "Faturalar", "source": "Bank A" },
    { "id": "txn_a_135", "date": "2025-10-08", "description": "Carrefour Express", "amount": 328, "type": "expense", "category": "Market", "source": "Bank A" },
    { "id": "txn_a_136", "date": "2025-10-06", "description": "Tim Hortons Kadıköy", "amount": 143, "type": "expense", "category": "Kahve", "source": "Bank A" },
    { "id": "txn_a_137", "date": "2025-10-04", "description": "BiTaksi", "amount": 297, "type": "expense", "category": "Ulaşım", "source": "Bank A" },
    { "id": "txn_a_138", "date": "2025-10-01", "description": "Maaş Ödemesi - Ekim", "amount": 70000, "type": "income", "category": "Maaş", "source": "Bank A" },
    { "id": "txn_a_139", "date": "2025-09-29", "description": "Migros Sanal Market", "amount": 688, "type": "expense", "category": "Market", "source": "Bank A" },
    { "id": "txn_a_140", "date": "2025-09-27", "description": "Yemeksepeti", "amount": 231, "type": "expense", "category": "Yemek", "source": "Bank A" },
    { "id": "txn_a_141", "date": "2025-09-25", "description": "Getir Market Büyük Sipariş", "amount": 374, "type": "expense", "category": "Market", "source": "Bank A" },
    { "id": "txn_a_142", "date": "2025-09-23", "description": "Starbucks Nişantaşı", "amount": 168, "type": "expense", "category": "Kahve", "source": "Bank A" },
    { "id": "txn_a_143", "date": "2025-09-21", "description": "Akaryakıt - Opet Beykoz", "amount": 900, "type": "expense", "category": "Ulaşım", "source": "Bank A" },
    { "id": "txn_a_144", "date": "2025-09-19", "description": "Elektrik Faturası - BEDAŞ", "amount": 496, "type": "expense", "category": "Faturalar", "source": "Bank A" },
    { "id": "txn_a_145", "date": "2025-09-17", "description": "A101 Market", "amount": 251, "type": "expense", "category": "Market", "source": "Bank A" },
    { "id": "txn_a_146", "date": "2025-09-15", "description": "Trendyol Yemek", "amount": 214, "type": "expense", "category": "Yemek", "source": "Bank A" },
    { "id": "txn_a_147", "date": "2025-09-13", "description": "Su Faturası - İSKİ", "amount": 149, "type": "expense", "category": "Faturalar", "source": "Bank A" },
    { "id": "txn_a_148", "date": "2025-09-11", "description": "Doğalgaz Faturası - İGDAŞ", "amount": 280, "type": "expense", "category": "Faturalar", "source": "Bank A" },
    { "id": "txn_a_149", "date": "2025-09-09", "description": "İETT İstanbulkart Yükleme", "amount": 200, "type": "expense", "category": "Ulaşım", "source": "Bank A" },
    { "id": "txn_a_150", "date": "2025-09-07", "description": "Kahve Dünyası Bağdat", "amount": 128, "type": "expense", "category": "Kahve", "source": "Bank A" },
    { "id": "txn_a_151", "date": "2025-09-05", "description": "BİM Market", "amount": 362, "type": "expense", "category": "Market", "source": "Bank A" },
    { "id": "txn_a_152", "date": "2025-09-03", "description": "Uber", "amount": 107, "type": "expense", "category": "Ulaşım", "source": "Bank A" },
    { "id": "txn_a_153", "date": "2025-09-01", "description": "Maaş Ödemesi - Eylül", "amount": 70000, "type": "income", "category": "Maaş", "source": "Bank A" },
    { "id": "txn_a_154", "date": "2025-08-30", "description": "Migros Sanal Market", "amount": 742, "type": "expense", "category": "Market", "source": "Bank A" },
    { "id": "txn_a_155", "date": "2025-08-28", "description": "Yemeksepeti", "amount": 298, "type": "expense", "category": "Yemek", "source": "Bank A" },
    { "id": "txn_a_156", "date": "2025-08-26", "description": "Starbucks Etiler", "amount": 179, "type": "expense", "category": "Kahve", "source": "Bank A" },
    { "id": "txn_a_157", "date": "2025-08-24", "description": "Akaryakıt - Shell Sarıyer", "amount": 940, "type": "expense", "category": "Ulaşım", "source": "Bank A" },
    { "id": "txn_a_158", "date": "2025-08-22", "description": "Getir Market Büyük Sipariş", "amount": 418, "type": "expense", "category": "Market", "source": "Bank A" },
    { "id": "txn_a_159", "date": "2025-08-20", "description": "Elektrik Faturası - BEDAŞ", "amount": 748, "type": "expense", "category": "Faturalar", "source": "Bank A" },
    { "id": "txn_a_160", "date": "2025-08-18", "description": "A101 Market", "amount": 274, "type": "expense", "category": "Market", "source": "Bank A" },
    { "id": "txn_a_161", "date": "2025-08-16", "description": "Trendyol Yemek", "amount": 209, "type": "expense", "category": "Yemek", "source": "Bank A" },
    { "id": "txn_a_162", "date": "2025-08-14", "description": "Su Faturası - İSKİ", "amount": 181, "type": "expense", "category": "Faturalar", "source": "Bank A" },
    { "id": "txn_a_163", "date": "2025-08-12", "description": "İETT İstanbulkart Yükleme", "amount": 200, "type": "expense", "category": "Ulaşım", "source": "Bank A" },
    { "id": "txn_a_164", "date": "2025-08-10", "description": "Tim Hortons Beşiktaş", "amount": 141, "type": "expense", "category": "Kahve", "source": "Bank A" },
    { "id": "txn_a_165", "date": "2025-08-08", "description": "Carrefour Express", "amount": 396, "type": "expense", "category": "Market", "source": "Bank A" },
    { "id": "txn_a_166", "date": "2025-08-06", "description": "BiTaksi", "amount": 301, "type": "expense", "category": "Ulaşım", "source": "Bank A" },
    { "id": "txn_a_167", "date": "2025-08-04", "description": "Doğalgaz Faturası - İGDAŞ", "amount": 220, "type": "expense", "category": "Faturalar", "source": "Bank A" },
    { "id": "txn_a_168", "date": "2025-08-01", "description": "Maaş Ödemesi - Ağustos", "amount": 70000, "type": "income", "category": "Maaş", "source": "Bank A" },
    { "id": "txn_a_169", "date": "2025-07-30", "description": "Migros Sanal Market", "amount": 814, "type": "expense", "category": "Market", "source": "Bank A" },
    { "id": "txn_a_170", "date": "2025-07-28", "description": "Yemeksepeti", "amount": 262, "type": "expense", "category": "Yemek", "source": "Bank A" },
    { "id": "txn_a_171", "date": "2025-07-26", "description": "Getir Market", "amount": 381, "type": "expense", "category": "Market", "source": "Bank A" },
    { "id": "txn_a_172", "date": "2025-07-24", "description": "Starbucks Beşiktaş", "amount": 164, "type": "expense", "category": "Kahve", "source": "Bank A" },
    { "id": "txn_a_173", "date": "2025-07-22", "description": "Akaryakıt - Opet Kadıköy", "amount": 870, "type": "expense", "category": "Ulaşım", "source": "Bank A" },
    { "id": "txn_a_174", "date": "2025-07-20", "description": "Elektrik Faturası - BEDAŞ", "amount": 820, "type": "expense", "category": "Faturalar", "source": "Bank A" },
    { "id": "txn_a_175", "date": "2025-07-18", "description": "A101 Market", "amount": 293, "type": "expense", "category": "Market", "source": "Bank A" },
    { "id": "txn_a_176", "date": "2025-07-16", "description": "Trendyol Yemek", "amount": 188, "type": "expense", "category": "Yemek", "source": "Bank A" },
    { "id": "txn_a_177", "date": "2025-07-14", "description": "Su Faturası - İSKİ", "amount": 171, "type": "expense", "category": "Faturalar", "source": "Bank A" },
    { "id": "txn_a_178", "date": "2025-07-12", "description": "İETT İstanbulkart Yükleme", "amount": 300, "type": "expense", "category": "Ulaşım", "source": "Bank A" },
    { "id": "txn_a_179", "date": "2025-07-10", "description": "Kahve Dünyası Moda", "amount": 135, "type": "expense", "category": "Kahve", "source": "Bank A" },
    { "id": "txn_a_180", "date": "2025-07-08", "description": "BİM Market", "amount": 414, "type": "expense", "category": "Market", "source": "Bank A" },
    { "id": "txn_a_181", "date": "2025-07-06", "description": "Doğalgaz Faturası - İGDAŞ", "amount": 185, "type": "expense", "category": "Faturalar", "source": "Bank A" },
    { "id": "txn_a_182", "date": "2025-07-04", "description": "Uber", "amount": 118, "type": "expense", "category": "Ulaşım", "source": "Bank A" },
    { "id": "txn_a_183", "date": "2025-07-01", "description": "Maaş Ödemesi - Temmuz", "amount": 70000, "type": "income", "category": "Maaş", "source": "Bank A" },
    { "id": "txn_a_184", "date": "2025-06-29", "description": "Migros Sanal Market", "amount": 678, "type": "expense", "category": "Market", "source": "Bank A" },
    { "id": "txn_a_185", "date": "2025-06-27", "description": "Getir Market Büyük Sipariş", "amount": 362, "type": "expense", "category": "Market", "source": "Bank A" },
    { "id": "txn_a_186", "date": "2025-06-25", "description": "Yemeksepeti", "amount": 247, "type": "expense", "category": "Yemek", "source": "Bank A" },
    { "id": "txn_a_187", "date": "2025-06-23", "description": "Starbucks Kadıköy", "amount": 157, "type": "expense", "category": "Kahve", "source": "Bank A" },
    { "id": "txn_a_188", "date": "2025-06-21", "description": "Akaryakıt - Shell Beşiktaş", "amount": 910, "type": "expense", "category": "Ulaşım", "source": "Bank A" },
    { "id": "txn_a_189", "date": "2025-06-19", "description": "Elektrik Faturası - BEDAŞ", "amount": 576, "type": "expense", "category": "Faturalar", "source": "Bank A" },
    { "id": "txn_a_190", "date": "2025-06-17", "description": "A101 Market", "amount": 287, "type": "expense", "category": "Market", "source": "Bank A" },
    { "id": "txn_a_191", "date": "2025-06-15", "description": "Doğalgaz Faturası - İGDAŞ", "amount": 210, "type": "expense", "category": "Faturalar", "source": "Bank A" },
    { "id": "txn_a_192", "date": "2025-06-13", "description": "Trendyol Yemek", "amount": 196, "type": "expense", "category": "Yemek", "source": "Bank A" },
    { "id": "txn_a_193", "date": "2025-06-11", "description": "İETT İstanbulkart Yükleme", "amount": 200, "type": "expense", "category": "Ulaşım", "source": "Bank A" },
    { "id": "txn_a_194", "date": "2025-06-09", "description": "Su Faturası - İSKİ", "amount": 143, "type": "expense", "category": "Faturalar", "source": "Bank A" },
    { "id": "txn_a_195", "date": "2025-06-07", "description": "Carrefour Express", "amount": 349, "type": "expense", "category": "Market", "source": "Bank A" },
    { "id": "txn_a_196", "date": "2025-06-05", "description": "Tim Hortons Üsküdar", "amount": 136, "type": "expense", "category": "Kahve", "source": "Bank A" },
    { "id": "txn_a_197", "date": "2025-06-03", "description": "BiTaksi", "amount": 292, "type": "expense", "category": "Ulaşım", "source": "Bank A" },
    { "id": "txn_a_198", "date": "2025-06-01", "description": "Maaş Ödemesi - Haziran", "amount": 70000, "type": "income", "category": "Maaş", "source": "Bank A" }
  ],
  "upcoming_payments": [
    { "id": "up_a_001", "due_date": "2026-06-01", "amount": 70000, "description": "Maaş Ödemesi - Haziran", "source": "Bank A" },
    { "id": "up_a_002", "due_date": "2026-05-20", "amount": 680, "description": "Elektrik Faturası - BEDAŞ", "source": "Bank A" },
    { "id": "up_a_003", "due_date": "2026-05-22", "amount": 430, "description": "Doğalgaz Faturası - İGDAŞ", "source": "Bank A" }
  ]
}